LICENSE
MANIFEST.in
README.rst
setup.py
pysword/__init__.py
pysword/bible.py
pysword/books.py
pysword/canon-parser.py
pysword/canons.py
pysword/cleaner.py
pysword/modules.py
pysword/sapphire.py
pysword/utils.py
pysword.egg-info/PKG-INFO
pysword.egg-info/SOURCES.txt
pysword.egg-info/dependency_links.txt
pysword.egg-info/top_level.txt