Metadata-Version: 1.1
Name: pysword
Version: 0.2.7
Summary: A native Python2/3 reader module for the SWORD Project Bible Modules
Home-page: https://gitlab.com/tgc-dk/pysword
Author: Tomas Groth
Author-email: second@tgc.dk
License: MIT
Platform: any
Classifier: Development Status :: 4 - Beta
Classifier: Intended Audience :: Religion
Classifier: Intended Audience :: Developers
Classifier: Operating System :: OS Independent
Classifier: Programming Language :: Python :: 2
Classifier: Programming Language :: Python :: 3
Classifier: Topic :: Religion
Classifier: Topic :: Software Development
Classifier: License :: OSI Approved :: MIT License
